rtd_poetry.py
rtd_poetry_tmp-0.1.2.dist-info/WHEEL
rtd_poetry_tmp-0.1.2.dist-info/METADATA
rtd_poetry_tmp-0.1.2.dist-info/RECORD
